odoo10_addon_web_hide_db_manager_link-10.0.1.0.0-py2.7-nspkg.pth
odoo10_addon_web_hide_db_manager_link-10.0.1.0.0.dist-info/top_level.txt
odoo10_addon_web_hide_db_manager_link-10.0.1.0.0.dist-info/WHEEL
odoo10_addon_web_hide_db_manager_link-10.0.1.0.0.dist-info/RECORD
odoo10_addon_web_hide_db_manager_link-10.0.1.0.0.dist-info/metadata.json
odoo10_addon_web_hide_db_manager_link-10.0.1.0.0.dist-info/DESCRIPTION.rst
odoo10_addon_web_hide_db_manager_link-10.0.1.0.0.dist-info/METADATA
odoo10_addon_web_hide_db_manager_link-10.0.1.0.0.dist-info/namespace_packages.txt
odoo/addons/web_hide_db_manager_link/__manifest__.py
odoo/addons/web_hide_db_manager_link/__init__.py
odoo/addons/web_hide_db_manager_link/README.rst
odoo/addons/web_hide_db_manager_link/views/webclient_templates.xml
odoo/addons/web_hide_db_manager_link/static/description/icon.svg
odoo/addons/web_hide_db_manager_link/static/description/icon.png
odoo/addons/web_hide_db_manager_link/static/src/img/screenshot.png
