Metadata-Version: 2.0
Name: odoo10-addon-web-hide-db-manager-link
Version: 10.0.1.0.0
Summary: Hide link to database manager in login screen
Home-page: http://anubia.es
Author: Alejandro Santana, Odoo Community Association (OCA)
Author-email: support@odoo-community.org
License: AGPL-3
Platform: UNKNOWN
Requires-Dist: odoo (<10.1dev,>=10.0)
Classifier: Programming Language :: Python :: 2.7
Classifier: Framework :: Odoo
Classifier: License :: OSI Approved :: GNU Affero General Public License v3
